pdat/__init__.py
pdat/pdat.py
pdat/pypsrfits.py
pdat/templates/search_scratch.fits
pdat/templates/search_template.fits
pdat-0.2.1.dist-info/AUTHORS.rst
pdat-0.2.1.dist-info/LICENSE
pdat-0.2.1.dist-info/METADATA
pdat-0.2.1.dist-info/WHEEL
pdat-0.2.1.dist-info/top_level.txt
pdat-0.2.1.dist-info/RECORD
