Metadata-Version: 2.1
Name: pdat
Version: 0.2.1
Summary: Python package for dealing with PSRFITS and other pulsar data files.
Home-page: https://github.com/hazboun6/PulsarDataToolbox
Author: Jeffrey S Hazboun
Author-email: jeffrey.hazboun@gmail.com
License: MIT License
Keywords: pdat
Platform: UNKNOWN
Classifier: Development Status :: 2 - Pre-Alpha
Classifier: Intended Audience :: Developers
Classifier: License :: OSI Approved :: MIT License
Classifier: Natural Language :: English
Classifier: Programming Language :: Python :: 3
Classifier: Programming Language :: Python :: 3.5
Classifier: Programming Language :: Python :: 3.6
Classifier: Programming Language :: Python :: 3.7
Requires-Dist: numpy (>=1.11)
Requires-Dist: fitsio (==0.9.12)
Requires-Dist: six (>=1.12.0)
